.travis.yml
AUTHORS
ChangeLog
LICENSE
README.md
setup.cfg
setup.py
tox.ini
jabstract/__init__.py
jabstract.egg-info/PKG-INFO
jabstract.egg-info/SOURCES.txt
jabstract.egg-info/dependency_links.txt
jabstract.egg-info/not-zip-safe
jabstract.egg-info/pbr.json
jabstract.egg-info/top_level.txt
test/__init__.py
test/test_jabstract.py