Metadata-Version: 1.1
Name: jabstract
Version: 0.1.2
Summary: Test tool for overridable json fixtures
Home-page: https://github.com/internap/jabstract
Author: Internap
Author-email: opensource@internap.com
License: UNKNOWN
Platform: UNKNOWN
Classifier: Development Status :: 4 - Beta
Classifier: Framework :: Pytest
Classifier: Intended Audience :: Developers
Classifier: License :: OSI Approved :: Apache Software License
Classifier: Operating System :: POSIX
Classifier: Programming Language :: Python :: 3.4
Classifier: Programming Language :: Python :: 3.5
Classifier: Programming Language :: Python :: 3.6
